odoo/addons/sale_order_product_recommendation_quick_add/README.rst
odoo/addons/sale_order_product_recommendation_quick_add/__init__.py
odoo/addons/sale_order_product_recommendation_quick_add/__manifest__.py
odoo/addons/sale_order_product_recommendation_quick_add/i18n/fr.po
odoo/addons/sale_order_product_recommendation_quick_add/i18n/it.po
odoo/addons/sale_order_product_recommendation_quick_add/i18n/sale_order_product_recommendation_quick_add.pot
odoo/addons/sale_order_product_recommendation_quick_add/models/__init__.py
odoo/addons/sale_order_product_recommendation_quick_add/models/sale_order.py
odoo/addons/sale_order_product_recommendation_quick_add/readme/CONTRIBUTORS.rst
odoo/addons/sale_order_product_recommendation_quick_add/readme/DESCRIPTION.rst
odoo/addons/sale_order_product_recommendation_quick_add/static/description/icon.png
odoo/addons/sale_order_product_recommendation_quick_add/static/description/index.html
odoo/addons/sale_order_product_recommendation_quick_add/tests/__init__.py
odoo/addons/sale_order_product_recommendation_quick_add/tests/test_recomendation_quick_add.py
odoo/addons/sale_order_product_recommendation_quick_add/views/sale_order_view.xml
odoo_addon_sale_order_product_recommendation_quick_add-16.0.1.1.0.dist-info/METADATA
odoo_addon_sale_order_product_recommendation_quick_add-16.0.1.1.0.dist-info/WHEEL
odoo_addon_sale_order_product_recommendation_quick_add-16.0.1.1.0.dist-info/top_level.txt
odoo_addon_sale_order_product_recommendation_quick_add-16.0.1.1.0.dist-info/RECORD
