Metadata-Version: 2.1
Name: odoo-addon-sale_order_product_recommendation_quick_add
Version: 16.0.1.1.0
Summary: Add recommended products to sale order in a single click
Home-page: https://github.com/OCA/sale-workflow
Author: Camptocamp, Odoo Community Association (OCA)
Author-email: support@odoo-community.org
License: AGPL-3
Classifier: Programming Language :: Python
Classifier: Framework :: Odoo
Classifier: Framework :: Odoo :: 16.0
Classifier: License :: OSI Approved :: GNU Affero General Public License v3
Requires-Python: >=3.10
Requires-Dist: odoo-addon-sale-order-product-recommendation<16.1dev,>=16.0dev
Requires-Dist: odoo<16.1dev,>=16.0a
